django_permission-1.0.4.dist-info/DESCRIPTION.rst
django_permission-1.0.4.dist-info/METADATA
django_permission-1.0.4.dist-info/RECORD
django_permission-1.0.4.dist-info/WHEEL
django_permission-1.0.4.dist-info/metadata.json
django_permission-1.0.4.dist-info/top_level.txt
django_permission-1.0.4.dist-info/zip-safe
permission/__init__.py
permission/apps.py
permission/backends.py
permission/compat.py
permission/conf.py
permission/handlers.py
permission/models.py
permission/decorators/__init__.py
permission/decorators/classbase.py
permission/decorators/functionbase.py
permission/decorators/methodbase.py
permission/decorators/permission_required.py
permission/decorators/utils.py
permission/logics/__init__.py
permission/logics/author.py
permission/logics/base.py
permission/logics/collaborators.py
permission/logics/groupin.py
permission/logics/oneself.py
permission/logics/staff.py
permission/templatetags/__init__.py
permission/templatetags/permissionif.py
permission/tests/__init__.py
permission/tests/compat.py
permission/tests/models.py
permission/tests/test_backends.py
permission/tests/test_handlers.py
permission/tests/utils.py
permission/tests/test_decorators/__init__.py
permission/tests/test_decorators/test_classbase.py
permission/tests/test_decorators/test_functionbase.py
permission/tests/test_decorators/test_methodbase.py
permission/tests/test_decorators/test_permission_required.py
permission/tests/test_decorators/utils.py
permission/tests/test_logics/__init__.py
permission/tests/test_logics/test_author.py
permission/tests/test_logics/test_base.py
permission/tests/test_logics/test_collaborators.py
permission/tests/test_logics/test_groupin.py
permission/tests/test_logics/test_oneself.py
permission/tests/test_logics/test_staff.py
permission/tests/test_templatetags/__init__.py
permission/tests/test_templatetags/test_permissionif.py
permission/tests/test_utils/__init__.py
permission/tests/test_utils/test_field_lookup.py
permission/tests/test_utils/test_handlers.py
permission/tests/test_utils/test_logics.py
permission/tests/test_utils/test_permissions.py
permission/utils/__init__.py
permission/utils/autodiscover.py
permission/utils/field_lookup.py
permission/utils/handlers.py
permission/utils/logics.py
